invenio_sip2/__init__.py
invenio_sip2/actions/__init__.py
invenio_sip2/actions/actions.py
invenio_sip2/actions/base.py
invenio_sip2/api.py
invenio_sip2/cli.py
invenio_sip2/config.py
invenio_sip2/datastore.py
invenio_sip2/decorators.py
invenio_sip2/errors.py
invenio_sip2/ext.py
invenio_sip2/handlers/__init__.py
invenio_sip2/handlers/api_handlers.py
invenio_sip2/handlers/base.py
invenio_sip2/handlers/utils.py
invenio_sip2/helpers.py
invenio_sip2/models.py
invenio_sip2/permissions.py
invenio_sip2/proxies.py
invenio_sip2/records/__init__.py
invenio_sip2/records/record.py
invenio_sip2/server.py
invenio_sip2/templates/invenio_sip2/base.html
invenio_sip2/templates/invenio_sip2/monitoring.html
invenio_sip2/translations/de/LC_MESSAGES/messages.po
invenio_sip2/translations/en/LC_MESSAGES/messages.po
invenio_sip2/translations/es/LC_MESSAGES/messages.po
invenio_sip2/translations/fr/LC_MESSAGES/messages.po
invenio_sip2/translations/it/LC_MESSAGES/messages.po
invenio_sip2/translations/messages.pot
invenio_sip2/translations/nl/LC_MESSAGES/messages.po
invenio_sip2/utils.py
invenio_sip2/version.py
invenio_sip2/views/__init__.py
invenio_sip2/views/rest.py
invenio_sip2/views/views.py
invenio_sip2-0.6.25.dist-info/AUTHORS.rst
invenio_sip2-0.6.25.dist-info/LICENSE
invenio_sip2-0.6.25.dist-info/METADATA
invenio_sip2-0.6.25.dist-info/WHEEL
invenio_sip2-0.6.25.dist-info/entry_points.txt
invenio_sip2-0.6.25.dist-info/RECORD
