Metadata-Version: 2.3
Name: invenio-sip2
Version: 0.6.25
Summary: Invenio module that add a SIP2 communication for library self-check service
License: AGPL-3.0
Author: Laurent Dubois
Author-email: <laurent.dubois@uclouvain.be>
Requires-Python: >=3.9.2, <3.13
Classifier: Environment :: Web Environment
Classifier: Intended Audience :: Developers
Classifier: License :: OSI Approved :: GNU Affero General Public License v3
Classifier: Operating System :: OS Independent
Classifier: Programming Language :: Python
Classifier: Topic :: Internet :: WWW/HTTP :: Dynamic Content
Classifier: Topic :: Software Development :: Libraries :: Python Modules
Classifier: Programming Language :: Python :: 3.9
Classifier: Programming Language :: Python :: 3.10
Classifier: Programming Language :: Python :: 3.11
Classifier: Programming Language :: Python :: 3.12
Classifier: Development Status :: 3 - Alpha
Requires-Dist: Flask (>=2.2.0,<4.0)
Requires-Dist: SQLAlchemy (>=1.4.0,<3.0)
Requires-Dist: SQLAlchemy-Utils (>=0.33.1)
Requires-Dist: invenio-access (>=2.0.0,<5.0.0)
Requires-Dist: invenio-base (>=2.0,<3.0)
Requires-Dist: invenio-i18n (>=2.0.0,<4.0.0)
Requires-Dist: jsonpickle (>=1.2)
Requires-Dist: psutil
Requires-Dist: pycountry (>=19.7.15)
Requires-Dist: python-dateutil
